nocloud/__init__.py
nocloud/__main__.py
nocloud-0.0.1.dist-info/LICENSE
nocloud-0.0.1.dist-info/METADATA
nocloud-0.0.1.dist-info/WHEEL
nocloud-0.0.1.dist-info/top_level.txt
nocloud-0.0.1.dist-info/RECORD
